pdf_extract_kit/__init__.py
pdf_extract_kit/version.py
pdf_extract_kit/dataset/__init__.py
pdf_extract_kit/dataset/dataset.py
pdf_extract_kit/registry/__init__.py
pdf_extract_kit/registry/registry.py
pdf_extract_kit/tasks/__init__.py
pdf_extract_kit/tasks/base_task.py
pdf_extract_kit/tasks/formula_detection/__init__.py
pdf_extract_kit/tasks/formula_detection/task.py
pdf_extract_kit/tasks/formula_detection/models/yolo.py
pdf_extract_kit/tasks/formula_recognition/__init__.py
pdf_extract_kit/tasks/formula_recognition/task.py
pdf_extract_kit/tasks/formula_recognition/models/unimernet.py
pdf_extract_kit/tasks/layout_detection/__init__.py
pdf_extract_kit/tasks/layout_detection/task.py
pdf_extract_kit/tasks/layout_detection/models/__init__.py
pdf_extract_kit/tasks/layout_detection/models/layoutlmv3.py
pdf_extract_kit/tasks/layout_detection/models/yolo.py
pdf_extract_kit/tasks/layout_detection/models/layoutlmv3_util/backbone.py
pdf_extract_kit/tasks/layout_detection/models/layoutlmv3_util/beit.py
pdf_extract_kit/tasks/layout_detection/models/layoutlmv3_util/deit.py
pdf_extract_kit/tasks/layout_detection/models/layoutlmv3_util/model_init.py
pdf_extract_kit/tasks/layout_detection/models/layoutlmv3_util/rcnn_vl.py
pdf_extract_kit/tasks/layout_detection/models/layoutlmv3_util/visualizer.py
pdf_extract_kit/tasks/layout_detection/models/layoutlmv3_util/layoutlmft/__init__.py
pdf_extract_kit/tasks/layout_detection/models/layoutlmv3_util/layoutlmft/data/__init__.py
pdf_extract_kit/tasks/layout_detection/models/layoutlmv3_util/layoutlmft/data/cord.py
pdf_extract_kit/tasks/layout_detection/models/layoutlmv3_util/layoutlmft/data/data_collator.py
pdf_extract_kit/tasks/layout_detection/models/layoutlmv3_util/layoutlmft/data/funsd.py
pdf_extract_kit/tasks/layout_detection/models/layoutlmv3_util/layoutlmft/data/image_utils.py
pdf_extract_kit/tasks/layout_detection/models/layoutlmv3_util/layoutlmft/data/xfund.py
pdf_extract_kit-0.1.0.dist-info/LICENSE.md
pdf_extract_kit-0.1.0.dist-info/METADATA
pdf_extract_kit-0.1.0.dist-info/WHEEL
pdf_extract_kit-0.1.0.dist-info/top_level.txt
pdf_extract_kit-0.1.0.dist-info/RECORD
