Metadata-Version: 2.1
Name: pdf-extract-kit
Version: 0.1.0
Summary: A Comprehensive Toolkit for High-Quality PDF Content Extraction.
Author-email: Bin Wang <ictwangbin@gmail.com>
License: GNU AFFERO GENERAL PUBLIC LICENSE
Project-URL: Homepage, https://github.com/ledboot/PDF-Extract-Kit
Project-URL: Repository, https://github.com/ledboot/PDF-Extract-Kit
Project-URL: Issues, https://github.com/ledboot/PDF-Extract-Kit/issues
Keywords: pdf,ocr,layout-analysis,formula-recognition,content-extraction
Classifier: Programming Language :: Python :: 3
Classifier: License :: OSI Approved :: GNU Affero General Public License v3
Classifier: Operating System :: OS Independent
Classifier: Topic :: Scientific/Engineering :: Artificial Intelligence
Requires-Python: >=3.10
License-File: LICENSE.md
Requires-Dist: omegaconf
Requires-Dist: matplotlib
Requires-Dist: pymupdf
Requires-Dist: ultralytics>=8.2.85
Requires-Dist: doclayout-yolo>=0.0.2b1
Requires-Dist: unimernet==0.2.1
Requires-Dist: paddleocr==2.7.3
Requires-Dist: struct-eqtable
Requires-Dist: opencv-python>=4.6.0
Requires-Dist: pyyaml
Provides-Extra: cpu
Requires-Dist: paddlepaddle; extra == "cpu"
Provides-Extra: gpu
Requires-Dist: paddlepaddle-gpu; extra == "gpu"
Requires-Dist: lmdeploy; extra == "gpu"
Provides-Extra: layout
Requires-Dist: transformers; extra == "layout"
